cynthion/__init__.py
cynthion/board.py
cynthion/cynthion.py
cynthion/errors.py
cynthion/interface.py
cynthion/shared.py
cynthion/assets/54-cynthion.rules
cynthion/assets/apollo.bin
cynthion/assets/moondancer.bin
cynthion/assets/CynthionPlatformRev0D1/analyzer.bit
cynthion/assets/CynthionPlatformRev0D1/facedancer.bit
cynthion/assets/CynthionPlatformRev0D1/selftest.bit
cynthion/assets/CynthionPlatformRev0D2/analyzer.bit
cynthion/assets/CynthionPlatformRev0D2/facedancer.bit
cynthion/assets/CynthionPlatformRev0D2/selftest.bit
cynthion/assets/CynthionPlatformRev0D3/analyzer.bit
cynthion/assets/CynthionPlatformRev0D3/facedancer.bit
cynthion/assets/CynthionPlatformRev0D3/selftest.bit
cynthion/assets/CynthionPlatformRev0D4/analyzer.bit
cynthion/assets/CynthionPlatformRev0D4/facedancer.bit
cynthion/assets/CynthionPlatformRev0D4/selftest.bit
cynthion/assets/CynthionPlatformRev0D5/facedancer.bit
cynthion/assets/CynthionPlatformRev0D5/selftest.bit
cynthion/assets/CynthionPlatformRev0D6/facedancer.bit
cynthion/assets/CynthionPlatformRev0D6/selftest.bit
cynthion/assets/CynthionPlatformRev0D7/facedancer.bit
cynthion/assets/CynthionPlatformRev0D7/selftest.bit
cynthion/assets/CynthionPlatformRev1D0/facedancer.bit
cynthion/assets/CynthionPlatformRev1D0/selftest.bit
cynthion/assets/CynthionPlatformRev1D1/facedancer.bit
cynthion/assets/CynthionPlatformRev1D1/selftest.bit
cynthion/assets/CynthionPlatformRev1D2/facedancer.bit
cynthion/assets/CynthionPlatformRev1D2/selftest.bit
cynthion/assets/CynthionPlatformRev1D3/facedancer.bit
cynthion/assets/CynthionPlatformRev1D3/selftest.bit
cynthion/assets/CynthionPlatformRev1D4/analyzer.bit
cynthion/assets/CynthionPlatformRev1D4/facedancer.bit
cynthion/assets/CynthionPlatformRev1D4/selftest.bit
cynthion/boards/__init__.py
cynthion/boards/cynthion_moondancer.py
cynthion/commands/__init__.py
cynthion/commands/cli.py
cynthion/commands/cynthion_build.py
cynthion/commands/cynthion_flash.py
cynthion/commands/cynthion_info.py
cynthion-0.2.4.dist-info/licenses/LICENSE.txt
cynthion-0.2.4.dist-info/METADATA
cynthion-0.2.4.dist-info/WHEEL
cynthion-0.2.4.dist-info/entry_points.txt
cynthion-0.2.4.dist-info/top_level.txt
cynthion-0.2.4.dist-info/RECORD
